kanbanize_sdk/__init__.py
kanbanize_sdk/client.py
kanbanize_sdk/dataclasses.py
kanbanize_sdk/endpoints/__init__.py
kanbanize_sdk/endpoints/board_assignees.py
kanbanize_sdk/endpoints/board_block_reasons.py
kanbanize_sdk/endpoints/board_card_templates.py
kanbanize_sdk/endpoints/board_card_types.py
kanbanize_sdk/endpoints/board_child_parent_cards.py
kanbanize_sdk/endpoints/board_custom_field_allowed_values.py
kanbanize_sdk/endpoints/board_custom_field_default_contributors.py
kanbanize_sdk/endpoints/board_custom_fields.py
kanbanize_sdk/endpoints/board_discard_reasons.py
kanbanize_sdk/endpoints/board_history.py
kanbanize_sdk/endpoints/board_settings.py
kanbanize_sdk/endpoints/board_stickers.py
kanbanize_sdk/endpoints/board_structure.py
kanbanize_sdk/endpoints/board_structure_revisions.py
kanbanize_sdk/endpoints/board_tags.py
kanbanize_sdk/endpoints/board_teams.py
kanbanize_sdk/endpoints/board_visible_standard_fields.py
kanbanize_sdk/endpoints/boards.py
kanbanize_sdk/endpoints/cell_limits.py
kanbanize_sdk/endpoints/columns.py
kanbanize_sdk/endpoints/generics.py
kanbanize_sdk/endpoints/lane_section_limits.py
kanbanize_sdk/endpoints/lanes.py
kanbanize_sdk/endpoints/managed_workspaces.py
kanbanize_sdk/endpoints/merged_areas.py
kanbanize_sdk/endpoints/teams.py
kanbanize_sdk/endpoints/users.py
kanbanize_sdk/endpoints/workflows.py
kanbanize_sdk/endpoints/workspace_history.py
kanbanize_sdk/endpoints/workspace_managers.py
kanbanize_sdk/endpoints/workspaces.py
kanbanize_sdk/utils.py
kanbanize_sdk/wrapper.py
kanbanize_sdk-0.2.12.dist-info/LICENSE
kanbanize_sdk-0.2.12.dist-info/METADATA
kanbanize_sdk-0.2.12.dist-info/WHEEL
kanbanize_sdk-0.2.12.dist-info/RECORD
